setup.py
digExtractionClassifier.egg-info/PKG-INFO
digExtractionClassifier.egg-info/SOURCES.txt
digExtractionClassifier.egg-info/dependency_links.txt
digExtractionClassifier.egg-info/requires.txt
digExtractionClassifier.egg-info/top_level.txt
digExtractionsClassifier/__init__.py
digExtractionsClassifier/classify_extractions.py
digExtractionsClassifier/dig_extractions_classifier.py
digExtractionsClassifier/invoke_train_classifier.py
digExtractionsClassifier/train_classifier.py
digExtractionsClassifier/preprocessing/__init__.py
digExtractionsClassifier/preprocessing/semantic_type_marker.py
digExtractionsClassifier/utility/__init__.py
digExtractionsClassifier/utility/functions.py
test/test_extractions_classification.py