Metadata-Version: 1.1
Name: digExtractionClassifier
Version: 0.3.3
Summary: digExtractionClassifier
Home-page: https://github.com/usc-isi-i2/dig-extractions-classifier
Author: Rahul Kapoor
Author-email: rahulkap@isi.edu
License: UNKNOWN
Download-URL: https://github.com/usc-isi-i2/dig-extractions-classifier
Platform: UNKNOWN
